setup.cfg
setup.py
unitrail/__init__.py
unitrail/__main__.py
unitrail/__utils.py
unitrail/logging_utils.py
unitrail/results_formatter.py
unitrail/testrail_api.py
unitrail/testrail_filter.py
unitrail.egg-info/PKG-INFO
unitrail.egg-info/SOURCES.txt
unitrail.egg-info/dependency_links.txt
unitrail.egg-info/entry_points.txt
unitrail.egg-info/requires.txt
unitrail.egg-info/top_level.txt