Metadata-Version: 2.1
Name: unitrail
Version: 0.0.3
Summary: CLI for autotests connection with Testrail
Home-page: https://github.com/mettizik/unitrail
Author: Mokych Andrey
Author-email: mokych.andrey@apriorit.com
License: MIT
Keywords: testrail junit autotests report
Platform: UNKNOWN
Requires-Python: >=3.0
